soteria/__init__.py
soteria/module.py
soteria/soteria_scheduler.py
soteria/web_service.py
soteria/handlers/__init__.py
soteria/handlers/comms.py
soteria/handlers/db.py
soteria/handlers/db_interface.py
soteria/handlers/encryption.py
soteria/handlers/jira.py
soteria/handlers/logging.py
soteria/handlers/scheduler.py
soteria/templates/job_source.html
soteria/templates/job_source_2.html
soteria/templates/jobs.html
soteria/templates/specific_job.html
soteria/templates/components/configuration.html
soteria/templates/components/footer.html
soteria/templates/components/header.html
soteria/templates/components/job_table.html
soteria/templates/components/nav_bar.html
soteria/templates/components/source.html
soteria-0.2.7.dist-info/LICENSE
soteria-0.2.7.dist-info/METADATA
soteria-0.2.7.dist-info/WHEEL
soteria-0.2.7.dist-info/top_level.txt
soteria-0.2.7.dist-info/RECORD
