Metadata-Version: 2.1
Name: soteria
Version: 0.2.7
Summary: Scheduling tool for system monitoring.
Home-page: https://github.com/euanacampbell/soteria
Download-URL: https://github.com/euanacampbell/soteria/archive/refs/heads/master.tar.gz
Author: Euan Campbell
Author-email: dev@euan.app
License: MIT
Keywords: schedule,task
Classifier: Development Status :: 3 - Alpha
Classifier: Intended Audience :: Developers
Classifier: Topic :: Software Development :: Build Tools
Classifier: License :: OSI Approved :: MIT License
Classifier: Programming Language :: Python :: 3
Classifier: Programming Language :: Python :: 3.4
Classifier: Programming Language :: Python :: 3.5
Classifier: Programming Language :: Python :: 3.6
License-File: LICENSE
Requires-Dist: holidays
Requires-Dist: PyMySQL
Requires-Dist: PyYAML
Requires-Dist: flask
Requires-Dist: pyodbc
